ilpqec/__init__.py
ilpqec/decoder.py
ilpqec/gurobi_backend.py
ilpqec/sinter_decoder.py
ilpqec/solver.py
ilpqec-0.1.0.dist-info/licenses/LICENSE
ilpqec-0.1.0.dist-info/METADATA
ilpqec-0.1.0.dist-info/WHEEL
ilpqec-0.1.0.dist-info/top_level.txt
ilpqec-0.1.0.dist-info/RECORD
