Metadata-Version: 2.4
Name: ilpqec
Version: 0.1.0
Summary: ILP-based Quantum Error Correction Decoder
Author: ILPQEC Contributors
License-Expression: MIT
Project-URL: Homepage, https://github.com/nzy1997/ILPQEC
Project-URL: Documentation, https://nzy1997.github.io/ILPQEC/
Project-URL: Repository, https://github.com/nzy1997/ILPQEC
Keywords: quantum-computing,quantum-error-correction,qec,decoder,ilp,mixed-integer-programming,pyomo
Classifier: Development Status :: 3 - Alpha
Classifier: Intended Audience :: Science/Research
Classifier: Programming Language :: Python :: 3
Classifier: Programming Language :: Python :: 3.9
Classifier: Programming Language :: Python :: 3.10
Classifier: Programming Language :: Python :: 3.11
Classifier: Programming Language :: Python :: 3.12
Classifier: Programming Language :: Python :: 3.13
Classifier: Topic :: Scientific/Engineering :: Physics
Requires-Python: >=3.9
License-File: LICENSE
Requires-Dist: numpy>=1.20
Requires-Dist: highspy>=1.10
Provides-Extra: pyomo
Requires-Dist: pyomo>=6.0; extra == "pyomo"
Provides-Extra: gurobi
Requires-Dist: gurobipy>=10.0; python_version < "3.13" and extra == "gurobi"
Provides-Extra: docs
Requires-Dist: mkdocs>=1.6; extra == "docs"
Requires-Dist: mkdocs-material>=9.5; extra == "docs"
Provides-Extra: scipy
Requires-Dist: scipy>=1.7; extra == "scipy"
Provides-Extra: stim
Requires-Dist: stim>=1.12; extra == "stim"
Provides-Extra: sinter
Requires-Dist: sinter>=1.12; extra == "sinter"
Requires-Dist: stim>=1.12; extra == "sinter"
Requires-Dist: numpy<2.3; extra == "sinter"
Provides-Extra: dev
Requires-Dist: pytest>=8.4.2; extra == "dev"
Requires-Dist: pytest-cov>=4.0; extra == "dev"
Requires-Dist: mypy>=1.0; extra == "dev"
Requires-Dist: ruff>=0.1; extra == "dev"
Requires-Dist: pyomo>=6.0; extra == "dev"
Requires-Dist: scipy>=1.7; extra == "dev"
Requires-Dist: stim>=1.12; extra == "dev"
Dynamic: license-file
